[
  {
    "id": 1,
    "Number": 1,
    "Title": "Alphabets, Letters and Words",
    "TitleSwa": "Alfabeti, Herufi na Maneno",
    "TitleFr": "Alphabet, lettres et mots",
    "TitlePt": "Alfabetos, Letras e Palavras",
    "TitleEs": "Alfabetos, Letras y Palabras",
    "Summary": "Learn the Arabic letters and words step by step with audio pronunciation helper",
    "SummarySwa": "Jifunze Herufi na Maneno ya Kiarabu hatua kwa hatua na kusaidiwa na sauti ya matamshi yake",
    "SummaryFr": "Apprendre les lettres et les mots arabes étape par étape grâce à une assistance audio à la prononciation",
    "SummaryPt": "Aprenda as letras e palavras árabes passo a passo com o auxiliar de pronúncia de áudio",
    "SummaryEs": "Aprenda las letras y palabras árabes paso a paso con el asistente de pronunciación de audio",
    "Image": "stages_s1",
    "Sort": 1
  },
  {
    "id": 2,
    "Number": 2,
    "Title": "Qur\u0027an Recitation",
    "TitleSwa": "Usomaji wa Qur\u0027an",
    "TitleFr": "Récitation du Coran",
    "TitlePt": "Recitação do Alcorão",
    "TitleEs": "Recitación del Corán",
    "Summary": "Learn how to read the Qur\u0027an verse by verse and word by word",
    "SummarySwa": "Jifunze Kusoma Qur\u0027an",
    "SummaryFr": "Apprenez à lire le Coran verset par verset et mot par mot.",
    "SummaryPt": "Aprenda a ler o Alcorão versículo por versículo e palavra por palavra.",
    "SummaryEs": "Aprende a leer el Corán verso por verso y palabra por palabra.",
    "Image": "stages_s2",
    "Sort": 2
  },
  {
    "id": 3,
    "Number": 3,
    "Title": "Tajweed",
    "TitleSwa": "Tajweed",
    "TitleFr": "Tajwid",
    "TitlePt": "Tajweed",
    "TitleEs": "Tajweed",
    "Summary": "Learning the rules of reading the Qur\u0027an (Tajweed) and color-coded Tajweed recitation with audio helper",
    "SummarySwa": "Jifunze Kanuni za Kusoma Qur\u0027an (Tajweed) na usomaji wa Qur’an kwa Tajweed kwa msaada wa Sauti.",
    "SummaryFr": "Apprendre les règles de lecture du Coran (Tajwid) et la récitation en Tajwid à code couleur avec assitance audio",
    "SummaryPt": "Aprendendo as regras de leitura do Alcorão (Tajweed) e recitação Tajweed codificada por cores com auxiliar de áudio",
    "SummaryEs": "Aprender las reglas de lectura del Corán (Tajweed) y la recitación de Tajweed codificada por colores con ayuda de audio",
    "Image": "stages_s3",
    "Sort": 4
  },
  {
    "id": 4,
    "Number": 4,
    "Title": "Qur\u0027anic Language",
    "TitleSwa": "Lugha ya Qur\u0027an",
    "TitleFr": "Langue du Coran",
    "TitlePt": "Língua do Alcorão",
    "TitleEs": "Idioma Coránico",
    "Summary": "Learning Arabic as the language of the Qur\u0027an with examples from the Qur\u0027an itself",
    "SummarySwa": "Jifunze Kiarabu ambayo ni lugha ya Qur’an kwa kutimia mifano kutaka kwenye Qur’an yenyewe.",
    "SummaryFr": "Apprendre l’arabe en tant que langue du Coran grâce à des exemples tirés du Coran",
    "SummaryPt": "Aprender árabe como a língua do Alcorão com exemplos do próprio Alcorão",
    "SummaryEs": "Aprendiendo árabe como el idioma del Corán con ejemplos del propio Corán",
    "Image": "stages_s4",
    "Sort": 6
  },
  {
    "id": 5,
    "Number": 5,
    "Title": "Meaning of the Qur\u0027an",
    "TitleSwa": "Maana za Maneno ya Qur\u0027an",
    "TitleFr": "Interprétation du Coran",
    "TitlePt": "Significado do Alcorão",
    "TitleEs": "Significado del Corán",
    "Summary": "Translation of the Qur\u0027an",
    "SummarySwa": "Tarjuma ya Qur’an",
    "SummaryFr": "Traduction du Coran",
    "SummaryPt": "Tradução do Alcorão",
    "SummaryEs": "Traducción del Corán",
    "Image": "stages_s5",
    "Sort": 3
  },
  {
    "id": 7,
    "Number": 6,
    "Title": "Memorizing the Qur\u0027an",
    "TitleSwa": "Kuhifadhi Qur\u0027an",
    "TitleFr": "Mémoriser le Coran",
    "TitlePt": "Memorizando o Alcorão",
    "TitleEs": "Memorizando el Corán",
    "Summary": "Memorizing the Qur\u0027an verse by verse",
    "SummarySwa": "Kuhifadhi Qur\u0027an aya kwa aya",
    "SummaryFr": "mémorisation du Qu\u0027ran verset par verset",
    "SummaryPt": "Versículo por versículo",
    "SummaryEs": "Verso por Verso",
    "Image": "stages_s6",
    "Sort": 5
  }
]